{
  "type": "jvpillage:hag_replacement",
  "base": [
    {
      "item": "minecraft:rotten_flesh"
    }
  ],
  "result": [
    {
      "item": "minecraft:bone_meal"
    },
    {
      "item": "minecraft:bone_meal"
    },
    {
      "item": "minecraft:bone_meal"
    },
    {
      "item": "minecraft:bone_meal"
    },
    {
      "item": "minecraft:porkchop"
    },
    {
      "item": "minecraft:porkchop"
    },
    {
      "item": "minecraft:porkchop"
    },
    {
      "type": "forge:nbt",
      "item": "minecraft:potion",
      "nbt": "{\"Potion\":\"jvpillage:vomit_inducer\"}"
    },
    {
      "type": "forge:nbt",
      "item": "minecraft:potion",
      "nbt": "{\"Potion\":\"jvpillage:vomit_inducer\"}"
    },
    {
      "type": "forge:nbt",
      "item": "minecraft:potion",
      "nbt": "{\"Potion\":\"jvpillage:witch_rot\"}"
    }
  ]
}